{
  "resourceType": "PlanDefinition",
  "id": "cf-1638454179391",
  "meta": {
    "versionId": "2",
    "lastUpdated": "2021-12-02T14:51:45.255+00:00",
    "source": "#kDkLTjTTam06J57S"
  },
  "text": {
    "status": "generated",
    "div": "<div xmlns=\"http://www.w3.org/1999/xhtml\">Voruntersuchungen<a name=\"mm\"/></div>"
  },
  "url": "http://example.org/PlanDefinition/voruntersuchungen",
  "name": "Voruntersuchungen",
  "title": "Voruntersuchungen",
  "type": {
    "coding": [
      {
        "system": "http://terminology.hl7.org/CodeSystem/plan-definition-type",
        "code": "clinical-protocol",
        "display": "Clinical Protocol"
      }
    ]
  },
  "status": "draft",
  "experimental": true,
  "action": [
    {
      "id": "step-1-outerGroup",
      "groupingBehavior": "logical-group",
      "selectionBehavior": "all",
      "requiredBehavior": "must-unless-documented",
      "cardinalityBehavior": "single",
      "action": [
        {
          "id": "step-1-1-every3months",
          "timingTiming": {
            "repeat": {
              "frequency": 1,
              "period": 3,
              "periodUnit": "mo"
            }
          },
          "groupingBehavior": "logical-group",
          "selectionBehavior": "all",
          "requiredBehavior": "must-unless-documented",
          "cardinalityBehavior": "single",
          "action": [
            {
              "title": "MSPT (MSFC)",
              "definitionCanonical": "http://example.org/ActivityDefinition/mspt"
            },
            {
              "title": "Therapiespezifische Maßnahmen",
              "definitionCanonical": "http://example.org/ActivityDefinition/therapiespezifische-maßnahmen"
            }
          ]
        },
        {
          "id": "step-1-2-every12months",
          "timingTiming": {
            "repeat": {
              "frequency": 1,
              "period": 12,
              "periodUnit": "mo"
            }
          },
          "groupingBehavior": "logical-group",
          "selectionBehavior": "all",
          "requiredBehavior": "must-unless-documented",
          "cardinalityBehavior": "single",
          "action": [
            {
              "title": "OCT (Optische Kohärenztomografie)",
              "definitionCanonical": "http://example.org/ActivityDefinition/oct"
            },
            {
              "title": "Ganganalyse",
              "definitionCanonical": "http://example.org/ActivityDefinition/ganganalyse"
            },
            {
              "title": "MRT",
              "condition": [
                {
                  "kind": "applicability",
                  "expression": {
                    "language": "text/cql",
                    "expression": "no current pregnancy"
                  }
                }
              ],
              "definitionCanonical": "http://example.org/ActivityDefinition/mrt"
            }
          ]
        }
      ]
    }
  ]
}
