{
  "resourceType": "PlanDefinition",
  "id": "cf-1638385970742",
  "url": "http://example.org/PlanDefinition/zusatzdiagnostik",
  "name": "Zusatzdiagnostik",
  "title": "Zusatzdiagnostik",
  "status": "draft",
  "experimental": true,
  "action": [
    {
      "selectionBehavior": "any",
      "requiredBehavior": "must-unless-documented",
      "cardinalityBehavior": "single",
      "action": [
        {
          "title": "Ganganalyse",
          "definitionCanonical": "http://example.org/ActivityDefinition/ganganalyse"
        },
        {
          "title": "OCT",
          "definitionCanonical": "http://example.org/ActivityDefinition/oct"
        },
        {
          "title": "MRT",
          "definitionCanonical": "http://example.org/ActivtyDefinition/mrt"
        },
        {
          "title": "Laboruntersuchung",
          "definitionCanonical": "http://example.org/ActivityDefinition/labor"
        },
        {
          "title": "MSPT",
          "definitionCanonical": "http://example.org/ActivityDefinition/mspt"
        }
      ]
    }
  ]
}
